{
  "day_number": 50,
  "references": "Leviticus 9-10 • Psalms 8 • Isaiah 50 • Luke 6",
  "word_count": 3019,
  "estimated_minutes": 15,
  "translation": "King James Version",
  "canon": "Protestant",
  "quote": {
    "verse": "Psalms 8:7",
    "text": "All sheep and oxen, yea, and the beasts of the field;",
    "reflection": "Read this line twice and let it slow the room down before anything else speaks."
  },
  "tomorrow_teaser": "Leviticus 11-12 • Psalms 9 • Isaiah 51 • Luke 7",
  "chapters": [
    {
      "book": "Leviticus",
      "chapter_number": 9,
      "chapter_title": "Leviticus 9",
      "verses": [
        {
          "verse": 1,
          "text": "And it came to pass on the eighth day, that Moses called Aaron and his sons, and the elders of Israel;"
        },
        {
          "verse": 2,
          "text": "And he said unto Aaron, Take thee a young calf for a sin offering, and a ram for a burnt offering, without blemish, and offer them before the LORD."
        },
        {
          "verse": 3,
          "text": "And unto the children of Israel thou shalt speak, saying, Take ye a kid of the goats for a sin offering; and a calf and a lamb, both of the first year, without blemish, for a burnt offering;"
        },
        {
          "verse": 4,
          "text": "Also a bullock and a ram for peace offerings, to sacrifice before the LORD; and a meat offering mingled with oil: for to day the LORD will appear unto you."
        },
        {
          "verse": 5,
          "text": "And they brought that which Moses commanded before the tabernacle of the congregation: and all the congregation drew near and stood before the LORD."
        },
        {
          "verse": 6,
          "text": "And Moses said, This is the thing which the LORD commanded that ye should do: and the glory of the LORD shall appear unto you."
        },
        {
          "verse": 7,
          "text": "And Moses said unto Aaron, Go unto the altar, and offer thy sin offering, and thy burnt offering, and make an atonement for thyself, and for the people: and offer the offering of the people, and make an atonement for them; as the LORD commanded."
        },
        {
          "verse": 8,
          "text": "Aaron therefore went unto the altar, and slew the calf of the sin offering, which was for himself."
        },
        {
          "verse": 9,
          "text": "And the sons of Aaron brought the blood unto him: and he dipped his finger in the blood, and put it upon the horns of the altar, and poured out the blood at the bottom of the altar:"
        },
        {
          "verse": 10,
          "text": "But the fat, and the kidneys, and the caul above the liver of the sin offering, he burnt upon the altar; as the LORD commanded Moses."
        },
        {
          "verse": 11,
          "text": "And the flesh and the hide he burnt with fire without the camp."
        },
        {
          "verse": 12,
          "text": "And he slew the burnt offering; and Aaron’s sons presented unto him the blood, which he sprinkled round about upon the altar."
        },
        {
          "verse": 13,
          "text": "And they presented the burnt offering unto him, with the pieces thereof, and the head: and he burnt them upon the altar."
        },
        {
          "verse": 14,
          "text": "And he did wash the inwards and the legs, and burnt them upon the burnt offering on the altar."
        },
        {
          "verse": 15,
          "text": "And he brought the people’s offering, and took the goat, which was the sin offering for the people, and slew it, and offered it for sin, as the first."
        },
        {
          "verse": 16,
          "text": "And he brought the burnt offering, and offered it according to the manner."
        },
        {
          "verse": 17,
          "text": "And he brought the meat offering, and took an handful thereof, and burnt it upon the altar, beside the burnt sacrifice of the morning."
        },
        {
          "verse": 18,
          "text": "He slew also the bullock and the ram for a sacrifice of peace offerings, which was for the people: and Aaron’s sons presented unto him the blood, which he sprinkled upon the altar round about,"
        },
        {
          "verse": 19,
          "text": "And the fat of the bullock and of the ram, the rump, and that which covereth the inwards, and the kidneys, and the caul above the liver:"
        },
        {
          "verse": 20,
          "text": "And they put the fat upon the breasts, and he burnt the fat upon the altar:"
        },
        {
          "verse": 21,
          "text": "And the breasts and the right shoulder Aaron waved for a wave offering before the LORD; as Moses commanded."
        },
        {
          "verse": 22,
          "text": "And Aaron lifted up his hand toward the people, and blessed them, and came down from offering of the sin offering, and the burnt offering, and peace offerings."
        },
        {
          "verse": 23,
          "text": "And Moses and Aaron went into the tabernacle of the congregation, and came out, and blessed the people: and the glory of the LORD appeared unto all the people."
        },
        {
          "verse": 24,
          "text": "And there came a fire out from before the LORD, and consumed upon the altar the burnt offering and the fat: which when all the people saw, they shouted, and fell on their faces."
        }
      ],
      "verse_count": 24,
      "word_count": 627
    },
    {
      "book": "Leviticus",
      "chapter_number": 10,
      "chapter_title": "Leviticus 10",
      "verses": [
        {
          "verse": 1,
          "text": "And Nadab and Abihu, the sons of Aaron, took either of them his censer, and put fire therein, and put incense thereon, and offered strange fire before the LORD, which he commanded them not."
        },
        {
          "verse": 2,
          "text": "And there went out fire from the LORD, and devoured them, and they died before the LORD."
        },
        {
          "verse": 3,
          "text": "Then Moses said unto Aaron, This is it that the LORD spake, saying, I will be sanctified in them that come nigh me, and before all the people I will be glorified. And Aaron held his peace."
        },
        {
          "verse": 4,
          "text": "And Moses called Mishael and Elzaphan, the sons of Uzziel the uncle of Aaron, and said unto them, Come near, carry your brethren from before the sanctuary out of the camp."
        },
        {
          "verse": 5,
          "text": "So they went near, and carried them in their coats out of the camp; as Moses had said."
        },
        {
          "verse": 6,
          "text": "And Moses said unto Aaron, and unto Eleazar and unto Ithamar, his sons, Uncover not your heads, neither rend your clothes; lest ye die, and lest wrath come upon all the people: but let your brethren, the whole house of Israel, bewail the burning which the LORD hath kindled."
        },
        {
          "verse": 7,
          "text": "And ye shall not go out from the door of the tabernacle of the congregation, lest ye die: for the anointing oil of the LORD is upon you. And they did according to the word of Moses."
        },
        {
          "verse": 8,
          "text": "And the LORD spake unto Aaron, saying,"
        },
        {
          "verse": 9,
          "text": "Do not drink wine nor strong drink, thou, nor thy sons with thee, when ye go into the tabernacle of the congregation, lest ye die: it shall be a statute for ever throughout your generations:"
        },
        {
          "verse": 10,
          "text": "And that ye may put difference between holy and unholy, and between unclean and clean;"
        },
        {
          "verse": 11,
          "text": "And that ye may teach the children of Israel all the statutes which the LORD hath spoken unto them by the hand of Moses."
        },
        {
          "verse": 12,
          "text": "And Moses spake unto Aaron, and unto Eleazar and unto Ithamar, his sons that were left, Take the meat offering that remaineth of the offerings of the LORD made by fire, and eat it without leaven beside the altar: for it is most holy:"
        },
        {
          "verse": 13,
          "text": "And ye shall eat it in the holy place, because it is thy due, and thy sons’ due, of the sacrifices of the LORD made by fire: for so I am commanded."
        },
        {
          "verse": 14,
          "text": "And the wave breast and heave shoulder shall ye eat in a clean place; thou, and thy sons, and thy daughters with thee: for they be thy due, and thy sons’ due, which are given out of the sacrifices of peace offerings of the children of Israel."
        },
        {
          "verse": 15,
          "text": "The heave shoulder and the wave breast shall they bring with the offerings made by fire of the fat, to wave it for a wave offering before the LORD; and it shall be thine, and thy sons’ with thee, by a statute for ever; as the LORD hath commanded."
        },
        {
          "verse": 16,
          "text": "And Moses diligently sought the goat of the sin offering, and, behold, it was burnt: and he was angry with Eleazar and Ithamar, the sons of Aaron which were left alive, saying,"
        },
        {
          "verse": 17,
          "text": "Wherefore have ye not eaten the sin offering in the holy place, seeing it is most holy, and God hath given it you to bear the iniquity of the congregation, to make atonement for them before the LORD?"
        },
        {
          "verse": 18,
          "text": "Behold, the blood of it was not brought in within the holy place: ye should indeed have eaten it in the holy place, as I commanded."
        },
        {
          "verse": 19,
          "text": "And Aaron said unto Moses, Behold, this day have they offered their sin offering and their burnt offering before the LORD; and such things have befallen me: and if I had eaten the sin offering to day, should it have been accepted in the sight of the LORD?"
        },
        {
          "verse": 20,
          "text": "And when Moses heard that, he was content."
        }
      ],
      "verse_count": 20,
      "word_count": 628
    },
    {
      "book": "Psalms",
      "chapter_number": 8,
      "chapter_title": "Psalms 8",
      "verses": [
        {
          "verse": 1,
          "text": "O LORD, our Lord, how excellent is thy name in all the earth! who hast set thy glory above the heavens."
        },
        {
          "verse": 2,
          "text": "Out of the mouth of babes and sucklings hast thou ordained strength because of thine enemies, that thou mightest still the enemy and the avenger."
        },
        {
          "verse": 3,
          "text": "When I consider thy heavens, the work of thy fingers, the moon and the stars, which thou hast ordained;"
        },
        {
          "verse": 4,
          "text": "What is man, that thou art mindful of him? and the son of man, that thou visitest him?"
        },
        {
          "verse": 5,
          "text": "For thou hast made him a little lower than the angels, and hast crowned him with glory and honour."
        },
        {
          "verse": 6,
          "text": "Thou madest him to have dominion over the works of thy hands; thou hast put all things under his feet:"
        },
        {
          "verse": 7,
          "text": "All sheep and oxen, yea, and the beasts of the field;"
        },
        {
          "verse": 8,
          "text": "The fowl of the air, and the fish of the sea, and whatsoever passeth through the paths of the seas."
        },
        {
          "verse": 9,
          "text": "O LORD our Lord, how excellent is thy name in all the earth!"
        }
      ],
      "verse_count": 9,
      "word_count": 166
    },
    {
      "book": "Isaiah",
      "chapter_number": 50,
      "chapter_title": "Isaiah 50",
      "verses": [
        {
          "verse": 1,
          "text": "Thus saith the LORD, Where is the bill of your mother’s divorcement, whom I have put away? or which of my creditors is it to whom I have sold you? Behold, for your iniquities have ye sold yourselves, and for your transgressions is your mother put away."
        },
        {
          "verse": 2,
          "text": "Wherefore, when I came, was there no man? when I called, was there none to answer? Is my hand shortened at all, that it cannot redeem? or have I no power to deliver? behold, at my rebuke I dry up the sea, I make the rivers a wilderness: their fish stinketh, because there is no water, and dieth for thirst."
        },
        {
          "verse": 3,
          "text": "I clothe the heavens with blackness, and I make sackcloth their covering."
        },
        {
          "verse": 4,
          "text": "The Lord GOD hath given me the tongue of the learned, that I should know how to speak a word in season to him that is weary: he wakeneth morning by morning, he wakeneth mine ear to hear as the learned."
        },
        {
          "verse": 5,
          "text": "The Lord GOD hath opened mine ear, and I was not rebellious, neither turned away back."
        },
        {
          "verse": 6,
          "text": "I gave my back to the smiters, and my cheeks to them that plucked off the hair: I hid not my face from shame and spitting."
        },
        {
          "verse": 7,
          "text": "For the Lord GOD will help me; therefore shall I not be confounded: therefore have I set my face like a flint, and I know that I shall not be ashamed."
        },
        {
          "verse": 8,
          "text": "He is near that justifieth me; who will contend with me? let us stand together: who is mine adversary? let him come near to me."
        },
        {
          "verse": 9,
          "text": "Behold, the Lord GOD will help me; who is he that shall condemn me? lo, they all shall wax old as a garment; the moth shall eat them up."
        },
        {
          "verse": 10,
          "text": "Who is among you that feareth the LORD, that obeyeth the voice of his servant, that walketh in darkness, and hath no light? let him trust in the name of the LORD, and stay upon his God."
        },
        {
          "verse": 11,
          "text": "Behold, all ye that kindle a fire, that compass yourselves about with sparks: walk in the light of your fire, and in the sparks that ye have kindled. This shall ye have of mine hand; ye shall lie down in sorrow."
        }
      ],
      "verse_count": 11,
      "word_count": 366
    },
    {
      "book": "Luke",
      "chapter_number": 6,
      "chapter_title": "Luke 6",
      "verses": [
        {
          "verse": 1,
          "text": "And it came to pass on the second sabbath after the first, that he went through the corn fields; and his disciples plucked the ears of corn, and did eat, rubbing them in their hands."
        },
        {
          "verse": 2,
          "text": "And certain of the Pharisees said unto them, Why do ye that which is not lawful to do on the sabbath days?"
        },
        {
          "verse": 3,
          "text": "And Jesus answering them said, Have ye not read so much as this, what David did, when himself was an hungred, and they which were with him;"
        },
        {
          "verse": 4,
          "text": "How he went into the house of God, and did take and eat the shewbread, and gave also to them that were with him; which it is not lawful to eat but for the priests alone?"
        },
        {
          "verse": 5,
          "text": "And he said unto them, That the Son of man is Lord also of the sabbath."
        },
        {
          "verse": 6,
          "text": "And it came to pass also on another sabbath, that he entered into the synagogue and taught: and there was a man whose right hand was withered."
        },
        {
          "verse": 7,
          "text": "And the scribes and Pharisees watched him, whether he would heal on the sabbath day; that they might find an accusation against him."
        },
        {
          "verse": 8,
          "text": "But he knew their thoughts, and said to the man which had the withered hand, Rise up, and stand forth in the midst. And he arose and stood forth."
        },
        {
          "verse": 9,
          "text": "Then said Jesus unto them, I will ask you one thing; Is it lawful on the sabbath days to do good, or to do evil? to save life, or to destroy it?"
        },
        {
          "verse": 10,
          "text": "And looking round about upon them all, he said unto the man, Stretch forth thy hand. And he did so: and his hand was restored whole as the other."
        },
        {
          "verse": 11,
          "text": "And they were filled with madness; and communed one with another what they might do to Jesus."
        },
        {
          "verse": 12,
          "text": "And it came to pass in those days, that he went out into a mountain to pray, and continued all night in prayer to God."
        },
        {
          "verse": 13,
          "text": "And when it was day, he called unto him his disciples: and of them he chose twelve, whom also he named apostles;"
        },
        {
          "verse": 14,
          "text": "Simon, (whom he also named Peter,) and Andrew his brother, James and John, Philip and Bartholomew,"
        },
        {
          "verse": 15,
          "text": "Matthew and Thomas, James the son of Alphaeus, and Simon called Zelotes,"
        },
        {
          "verse": 16,
          "text": "And Judas the brother of James, and Judas Iscariot, which also was the traitor."
        },
        {
          "verse": 17,
          "text": "And he came down with them, and stood in the plain, and the company of his disciples, and a great multitude of people out of all Judaea and Jerusalem, and from the sea coast of Tyre and Sidon, which came to hear him, and to be healed of their diseases;"
        },
        {
          "verse": 18,
          "text": "And they that were vexed with unclean spirits: and they were healed."
        },
        {
          "verse": 19,
          "text": "And the whole multitude sought to touch him: for there went virtue out of him, and healed them all."
        },
        {
          "verse": 20,
          "text": "And he lifted up his eyes on his disciples, and said, Blessed be ye poor: for yours is the kingdom of God."
        },
        {
          "verse": 21,
          "text": "Blessed are ye that hunger now: for ye shall be filled. Blessed are ye that weep now: for ye shall laugh."
        },
        {
          "verse": 22,
          "text": "Blessed are ye, when men shall hate you, and when they shall separate you from their company, and shall reproach you, and cast out your name as evil, for the Son of man’s sake."
        },
        {
          "verse": 23,
          "text": "Rejoice ye in that day, and leap for joy: for, behold, your reward is great in heaven: for in the like manner did their fathers unto the prophets."
        },
        {
          "verse": 24,
          "text": "But woe unto you that are rich! for ye have received your consolation."
        },
        {
          "verse": 25,
          "text": "Woe unto you that are full! for ye shall hunger. Woe unto you that laugh now! for ye shall mourn and weep."
        },
        {
          "verse": 26,
          "text": "Woe unto you, when all men shall speak well of you! for so did their fathers to the false prophets."
        },
        {
          "verse": 27,
          "text": "But I say unto you which hear, Love your enemies, do good to them which hate you,"
        },
        {
          "verse": 28,
          "text": "Bless them that curse you, and pray for them which despitefully use you."
        },
        {
          "verse": 29,
          "text": "And unto him that smiteth thee on the one cheek offer also the other; and him that taketh away thy cloak forbid not to take thy coat also."
        },
        {
          "verse": 30,
          "text": "Give to every man that asketh of thee; and of him that taketh away thy goods ask them not again."
        },
        {
          "verse": 31,
          "text": "And as ye would that men should do to you, do ye also to them likewise."
        },
        {
          "verse": 32,
          "text": "For if ye love them which love you, what thank have ye? for sinners also love those that love them."
        },
        {
          "verse": 33,
          "text": "And if ye do good to them which do good to you, what thank have ye? for sinners also do even the same."
        },
        {
          "verse": 34,
          "text": "And if ye lend to them of whom ye hope to receive, what thank have ye? for sinners also lend to sinners, to receive as much again."
        },
        {
          "verse": 35,
          "text": "But love ye your enemies, and do good, and lend, hoping for nothing again; and your reward shall be great, and ye shall be the children of the Highest: for he is kind unto the unthankful and to the evil."
        },
        {
          "verse": 36,
          "text": "Be ye therefore merciful, as your Father also is merciful."
        },
        {
          "verse": 37,
          "text": "Judge not, and ye shall not be judged: condemn not, and ye shall not be condemned: forgive, and ye shall be forgiven:"
        },
        {
          "verse": 38,
          "text": "Give, and it shall be given unto you; good measure, pressed down, and shaken together, and running over, shall men give into your bosom. For with the same measure that ye mete withal it shall be measured to you again."
        },
        {
          "verse": 39,
          "text": "And he spake a parable unto them, Can the blind lead the blind? shall they not both fall into the ditch?"
        },
        {
          "verse": 40,
          "text": "The disciple is not above his master: but every one that is perfect shall be as his master."
        },
        {
          "verse": 41,
          "text": "And why beholdest thou the mote that is in thy brother’s eye, but perceivest not the beam that is in thine own eye?"
        },
        {
          "verse": 42,
          "text": "Either how canst thou say to thy brother, Brother, let me pull out the mote that is in thine eye, when thou thyself beholdest not the beam that is in thine own eye? Thou hypocrite, cast out first the beam out of thine own eye, and then shalt thou see clearly to pull out the mote that is in thy brother’s eye."
        },
        {
          "verse": 43,
          "text": "For a good tree bringeth not forth corrupt fruit; neither doth a corrupt tree bring forth good fruit."
        },
        {
          "verse": 44,
          "text": "For every tree is known by his own fruit. For of thorns men do not gather figs, nor of a bramble bush gather they grapes."
        },
        {
          "verse": 45,
          "text": "A good man out of the good treasure of his heart bringeth forth that which is good; and an evil man out of the evil treasure of his heart bringeth forth that which is evil: for of the abundance of the heart his mouth speaketh."
        },
        {
          "verse": 46,
          "text": "And why call ye me, Lord, Lord, and do not the things which I say?"
        },
        {
          "verse": 47,
          "text": "Whosoever cometh to me, and heareth my sayings, and doeth them, I will shew you to whom he is like:"
        },
        {
          "verse": 48,
          "text": "He is like a man which built an house, and digged deep, and laid the foundation on a rock: and when the flood arose, the stream beat vehemently upon that house, and could not shake it: for it was founded upon a rock."
        },
        {
          "verse": 49,
          "text": "But he that heareth, and doeth not, is like a man that without a foundation built an house upon the earth; against which the stream did beat vehemently, and immediately it fell; and the ruin of that house was great."
        }
      ],
      "verse_count": 49,
      "word_count": 1232
    }
  ]
}