{
  "day_number": 19,
  "references": "Genesis 37-38 • Job 19 • Isaias 19 • Matthew 19",
  "word_count": 3551,
  "estimated_minutes": 17,
  "translation": "Douay-Rheims",
  "canon": "Roman Catholic",
  "quote": {
    "verse": "Matthew 19:2",
    "text": "And great multitudes followed him; and he healed them there.",
    "reflection": "Read it without rushing. The comfort is in the staying, not the sprinting."
  },
  "tomorrow_teaser": "Genesis 39-40 • Job 20 • Isaias 20 • Matthew 20",
  "chapters": [
    {
      "book": "Genesis",
      "chapter_number": 37,
      "chapter_title": "Genesis 37",
      "verses": [
        {
          "verse": 1,
          "text": "And Jacob dwelt in the land of Chanaan, wherein his father sojourned.*"
        },
        {
          "verse": 2,
          "text": "And these are his generations: *Joseph, when he was sixteen years old, was feeding the flock with his brethren, being but a boy: and he was with the sons of Bala and of Zelpha, his father's wives: and he accused his brethren to his father of a most wicked crime."
        },
        {
          "verse": 3,
          "text": "Now Israel loved Joseph above all his sons, because he had him in his old age: and he made him a coat of divers colours."
        },
        {
          "verse": 4,
          "text": "And his brethren seeing that he was loved by his father, more than all his sons, hated him, and could not speak peaceably to him."
        },
        {
          "verse": 5,
          "text": "Now it fell out also that he told his brethren a dream, that he had dreamed: which occasioned them to hate him the more."
        },
        {
          "verse": 6,
          "text": "And he said to them: Hear my dream which I dreamed."
        },
        {
          "verse": 7,
          "text": "I thought we were binding sheaves in the field: and my sheaf arose as it were, and stood, and your sheaves standing about bowed down before my sheaf."
        },
        {
          "verse": 8,
          "text": "His brethren answered: Shalt thou be our king? or shall we be subject to thy dominion? Therefore this matter of his dreams and words ministered nourishment to their envy and hatred."
        },
        {
          "verse": 9,
          "text": "He dreamed also another dream, which he told his brethren, saying: I saw in a dream, as it were the sun, and the moon, and eleven stars worshipping me."
        },
        {
          "verse": 10,
          "text": "And when he had told this to his father, and brethren, his father rebuked him, and said: What meaneth this dream that thou hast dreamed? shall I and thy mother, and thy brethren worship thee upon the earth?"
        },
        {
          "verse": 11,
          "text": "His brethren therefore envied him: but his father considered the thing with himself."
        },
        {
          "verse": 12,
          "text": "And when his brethren abode in Sichem, feeding their father's flocks,"
        },
        {
          "verse": 13,
          "text": "Israel said to him: Thy brethren feed the sheep in Sichem: come, I will send thee to them. And when he answered:"
        },
        {
          "verse": 14,
          "text": "I am ready: he said to him: Go, and see if all things be well with thy brethren, and the cattle: and bring me word again what is doing. So being sent from the vale of Hebron, he came to Sichem:"
        },
        {
          "verse": 15,
          "text": "And a man found him there wandering in the field, and asked what he sought."
        },
        {
          "verse": 16,
          "text": "But he answered: I seek my brethren, tell me where they feed the flocks."
        },
        {
          "verse": 17,
          "text": "And the man said to him: They are departed from this place: for I heard them say: Let us go to Dothain. And Joseph went forward after his brethren, and found them in Dothain."
        },
        {
          "verse": 18,
          "text": "And when they saw him afar off, before he came nigh them, they thought to kill him:"
        },
        {
          "verse": 19,
          "text": "And said one to another: Behold the dreamer cometh."
        },
        {
          "verse": 20,
          "text": "Come, let us kill him, and cast him into some old pit: and we will say: Some evil beast hath devoured him: and then it shall appear what his dreams avail him."
        },
        {
          "verse": 21,
          "text": "*And Ruben hearing this, endeavoured to deliver him out of their hands, end said:"
        },
        {
          "verse": 22,
          "text": "Do not take away his life, nor shed his blood: but cast him into this pit, that is in the wilderness, and keep your hands harmless: now he said this, being desirous to deliver him out of their hands and to restore him to his father."
        },
        {
          "verse": 23,
          "text": "And as soon as he came to his brethren, they forthwith stript him of his outside coat, that was of divers colours:"
        },
        {
          "verse": 24,
          "text": "And cast him into an old pit where there was no water."
        },
        {
          "verse": 25,
          "text": "And sitting down to eat bread, they saw some Ismaelites on their way coming from Galaad, with their camels, carrying spices, and balm, and myrrh to Egypt."
        },
        {
          "verse": 26,
          "text": "And Juda said to his brethren: What will it profit us to kill our brother, and conceal his blood?"
        },
        {
          "verse": 27,
          "text": "It is better that he be sold to the Ismaelites, and that our hands be not defiled: for he is our brother and our flesh. His brethren agreed to his words."
        },
        {
          "verse": 28,
          "text": "*And when the Madianite merchants passed by, they drew him out of the pit, and sold him to the Ismaelites, for twenty pieces of silver: and they led him into Egypt.**"
        },
        {
          "verse": 29,
          "text": "And Ruben returning to the pit, found not the boy:"
        },
        {
          "verse": 30,
          "text": "And rending his garments he went to his brethren, and said: The boy doth not appear, and whither shall I go?"
        },
        {
          "verse": 31,
          "text": "And they took his coat, and dipped it in the blood of a kid, which they had killed:"
        },
        {
          "verse": 32,
          "text": "Sending some to carry it to their father, and to say: This we have found: see whether it be thy son's coat, or not."
        },
        {
          "verse": 33,
          "text": "And the father acknowledging it, said: It is my son's coat, an evil wild beast hath eaten him, a beast hath devoured Joseph."
        },
        {
          "verse": 34,
          "text": "And tearing his garments, he put on sackcloth, mourning for his son a long time."
        },
        {
          "verse": 35,
          "text": "And all his children being gathered together to comfort their father in his sorrow, he would not receive comfort, but said: I will go down to my son into hell, mourning. And whilst he continued weeping,"
        },
        {
          "verse": 36,
          "text": "The Madianites sold Joseph in Egypt to Putiphar, an eunuch of Pharao, captain of the soldiers."
        }
      ],
      "verse_count": 36,
      "word_count": 846
    },
    {
      "book": "Genesis",
      "chapter_number": 38,
      "chapter_title": "Genesis 38",
      "verses": [
        {
          "verse": 1,
          "text": "At that time Juda went down from his brethren, and turned in to a certain Odollamite, named Hiras."
        },
        {
          "verse": 2,
          "text": "*And he saw there the daughter of a man of Chanaan, called Sue: and taking her to wife, he went in unto her."
        },
        {
          "verse": 3,
          "text": "And she conceived, and bore a son, and called his name Her."
        },
        {
          "verse": 4,
          "text": "*And conceiving again, she bore a son, and called him Onan."
        },
        {
          "verse": 5,
          "text": "She bore also a third: whom she called Sela. After whose birth, she ceased to bear any more."
        },
        {
          "verse": 6,
          "text": "And Juda took a wife for Her, his first-born, whose name was Thamar."
        },
        {
          "verse": 7,
          "text": "*And Her, the first-born of Juda, was wicked in the sight of the Lord: and was slain by him."
        },
        {
          "verse": 8,
          "text": "Juda, therefore said to Onan his son: Go in to thy brother's wife and marry her, that thou mayst raise seed to thy brother."
        },
        {
          "verse": 9,
          "text": "He knowing that the children should not be his, when he went in to his brother's wife, spilled his seed upon the ground, lest children should be born in his brother's name."
        },
        {
          "verse": 10,
          "text": "And therefore the Lord slew him, because he did a detestable thing:"
        },
        {
          "verse": 11,
          "text": "Wherefore Juda said to Thamar his daughter- in-law: Remain a widow in thy father's house, till Sela my son grow up: for he was afraid lest he also might die, as his brethren did. She went her way, and dwelt in her father's house."
        },
        {
          "verse": 12,
          "text": "And after many days were past, the daughter of Sue the wife of Juda died: and when he had taken comfort after his mourning, he went up to Thamnas, to the shearers of his sheep, he and Hiras the Odollamite, the shepherd of his flock."
        },
        {
          "verse": 13,
          "text": "And it was told Thamar that her father-in-law was come up to Thamnas to shear his sheep."
        },
        {
          "verse": 14,
          "text": "And she put off the garments of her widowhood, and took a veil: and changing her dress, sat in the cross way, that leadeth to Thamnas: because Sela was grown up, and she had not been married to him."
        },
        {
          "verse": 15,
          "text": "When Juda saw her, he thought she was a harlot: for she had covered her face, lest she should be known."
        },
        {
          "verse": 16,
          "text": "And going to her, he said: Suffer me to lie with thee: for he knew her not to be his daughter-in-law. And she answered: What wilt thou give me to enjoy my company?"
        },
        {
          "verse": 17,
          "text": "He said: I will send thee a kid out of the flock. And when she said again: I will suffer what thou wilt, if thou give a pledge, till thou send what thou promisest."
        },
        {
          "verse": 18,
          "text": "Juda said: What wilt thou have for a pledge? She answered: Thy ring and bracelet, and the staff which thou holdest in thy hand. The woman therefore at one copulation conceived."
        },
        {
          "verse": 19,
          "text": "And she arose and went her way: and putting off the apparel which she had taken, put on the garments of her widowhood."
        },
        {
          "verse": 20,
          "text": "And Juda sent a kid by his shepherd, the Odollamite, that he might receive the pledge again, which he had given to the woman: but he, not finding her,"
        },
        {
          "verse": 21,
          "text": "Asked the men of that place: Where is the woman that sat in the cross way? And when they all made answer: There was no harlot in this place,"
        },
        {
          "verse": 22,
          "text": "He returned to Juda, and said to him: I have not found her; moreover the men of that place said to me, that there never sat a harlot there."
        },
        {
          "verse": 23,
          "text": "Juda said: Let her take it to herself; surely she cannot charge us with a lie, I sent the kid which I promised: and thou didst not find her."
        },
        {
          "verse": 24,
          "text": "And behold, after three months, they told Juda, saying: Thamar, thy daughter-in-law hath played the harlot, and she appeareth to have a big belly. And Juda said: Bring her out that she may be burnt."
        },
        {
          "verse": 25,
          "text": "But when she was led to execution, she sent to her father-in-law, saying: By the man, to whom these things belong, I am with child. See whose ring, and bracelet, and staff this is."
        },
        {
          "verse": 26,
          "text": "But he acknowledging the gifts, said: She is juster than I: because I did not give her to Sela, my son. However, he knew her no more."
        },
        {
          "verse": 27,
          "text": "*And when she was ready to be brought to bed, there appeared twins in her womb: and in the very delivery of the infants, one put forth a hand, whereon the midwife tied a scarlet thread, saying:"
        },
        {
          "verse": 28,
          "text": "This shall come forth the first."
        },
        {
          "verse": 29,
          "text": "But he drawing back his hand, the other came forth: and the woman said: Why is the partition divided for thee? and therefore called his name Phares."
        },
        {
          "verse": 30,
          "text": "*Afterwards his brother came out, on whose hand was the scarlet thread: and she called him Zara."
        }
      ],
      "verse_count": 30,
      "word_count": 768
    },
    {
      "book": "Job",
      "chapter_number": 19,
      "chapter_title": "Job 19",
      "verses": [
        {
          "verse": 1,
          "text": "Then Job answered , and said:"
        },
        {
          "verse": 2,
          "text": "How long do you afflict my soul, and break me in pieces with words?"
        },
        {
          "verse": 3,
          "text": "Behold, these ten times you confound me, and are not ashamed to oppress me."
        },
        {
          "verse": 4,
          "text": "For if I have been ignorant, my ignorance shall be with me."
        },
        {
          "verse": 5,
          "text": "But you have set yourselves up against me, and reprove me with my reproaches."
        },
        {
          "verse": 6,
          "text": "At least now understand, that God hath not afflicted me with an equal judgment, and compassed me with his scourges."
        },
        {
          "verse": 7,
          "text": "Behold I cry, suffering violence, and no one will hear: I shall cry aloud, and there is none to judge."
        },
        {
          "verse": 8,
          "text": "He hath hedged in my path round about, and I cannot pass, and in my way he hath set darkness."
        },
        {
          "verse": 9,
          "text": "He hath stript me of my glory, and hath taken the crown from my head."
        },
        {
          "verse": 10,
          "text": "He hath destroyed me on every side, and I am lost; and he hath taken away my hope, as from a tree that is plucked up."
        },
        {
          "verse": 11,
          "text": "His wrath is kindled against me, and he hath counted me as his enemy."
        },
        {
          "verse": 12,
          "text": "His troops have come together, and have made themselves a way by me, and have besieged my tabernacle round about."
        },
        {
          "verse": 13,
          "text": "He hath put my brethren far from me, and my acquaintance, like strangers, have departed from me."
        },
        {
          "verse": 14,
          "text": "My kinsmen have forsaken me, and they that knew me have forgotten me."
        },
        {
          "verse": 15,
          "text": "They that dwelt in my house, and my maid-servants, have counted me a stranger, and I have been like an alien in their eyes."
        },
        {
          "verse": 16,
          "text": "I called my servant, and he gave me no answer, I entreated him with my own mouth."
        },
        {
          "verse": 17,
          "text": "My wife hath abhorred my breath, and I entreated the children of my womb."
        },
        {
          "verse": 18,
          "text": "Even fools despise me; and when I was gone from them, they spoke against me."
        },
        {
          "verse": 19,
          "text": "They that were some time my counsellors, have abhorred me: and he whom I loved most, is turned against me."
        },
        {
          "verse": 20,
          "text": "The flesh being consumed, my bone hath cleaved to my skin, and nothing but lips are left about my teeth."
        },
        {
          "verse": 21,
          "text": "Have pity on me, have pity on me, at least you, my friends, because the hand of the Lord hath touched me."
        },
        {
          "verse": 22,
          "text": "Why do you persecute me as God, and glut yourselves with my flesh?"
        },
        {
          "verse": 23,
          "text": "Who will grant me that my words may be written? who will grant me that they may be marked down in a book:"
        },
        {
          "verse": 24,
          "text": "With an iron pen, and in a plate of lead, or else be graven with an instrument in flint-stone."
        },
        {
          "verse": 25,
          "text": "For I know that my Redeemer liveth, and in the last day I shall rise out of the earth."
        },
        {
          "verse": 26,
          "text": "And I shall be clothed again with my skin, and in my flesh I will see my God."
        },
        {
          "verse": 27,
          "text": "Whom I myself shall see, and my eyes shall behold, and not another: this, my hope, is laid up in my bosom."
        },
        {
          "verse": 28,
          "text": "Why then do you say now: Let us persecute him, and let us find occasion of word against him?"
        },
        {
          "verse": 29,
          "text": "Flee then from the face of the sword, for the sword is the revenger of iniquities: and know ye that there is judgment."
        }
      ],
      "verse_count": 29,
      "word_count": 512
    },
    {
      "book": "Isaias",
      "chapter_number": 19,
      "chapter_title": "Isaias 19",
      "verses": [
        {
          "verse": 1,
          "text": "The burden of Egypt. Behold the Lord will ascend upon a swift cloud, and will enter into Egypt, and the idols of Egypt shall be moved at his presence, and the heart of Egypt shall melt in the midst thereof."
        },
        {
          "verse": 2,
          "text": "And I will set the Egyptians to fight against the Egyptians: and they shall fight brother against brother, and friend against friend, city against city, kingdom against kingdom."
        },
        {
          "verse": 3,
          "text": "And the spirit of Egypt shall be broken in the bowels thereof, and I will cast down their counsel: and they shall consult their idols, and their diviners, and their wizards and soothsayers."
        },
        {
          "verse": 4,
          "text": "And I will deliver Egypt into the hand of cruel masters, and a strong king shall rule over them, saith the Lord, the God of hosts."
        },
        {
          "verse": 5,
          "text": "And the water of the sea shall be dried up, and the rivers shall be wasted and dry."
        },
        {
          "verse": 6,
          "text": "And the rivers shall fail: the streams of the banks shall be diminished, and be dried up. The reed and the bulrush shall wither away."
        },
        {
          "verse": 7,
          "text": "The channel of the river shall be laid bare from its fountain; and every thing sown by the water shall be dried up; it shall wither away, and shall be no more."
        },
        {
          "verse": 8,
          "text": "The fishers also shall mourn: and all that cast a hook into the river shall lament; and they that spread nets upon the waters shall languish away."
        },
        {
          "verse": 9,
          "text": "They shall be confounded that wrought in flax, combing and weaving fine linen."
        },
        {
          "verse": 10,
          "text": "And its watery places shall be dry; all they shall mourn that made pools to take fishes."
        },
        {
          "verse": 11,
          "text": "The princes of Tanis are become fools; the wise counsellors of Pharao have given foolish counsel: how will you say to Pharao: I am the son of the wise, the son of ancient kings?"
        },
        {
          "verse": 12,
          "text": "Where are now thy wise men? let them tell thee, and shew what the Lord of hosts hath purposed upon Egypt."
        },
        {
          "verse": 13,
          "text": "The princes of Tanis are become fools; the princes of Memphis are gone astray; they have deceived Egypt, the stay of the people thereof."
        },
        {
          "verse": 14,
          "text": "The Lord hath mingled in the midst thereof the spirit of giddiness: and they have caused Egypt to err in all his works, as a drunken man staggereth and vomiteth."
        },
        {
          "verse": 15,
          "text": "And there shall be no work for Egypt, to make head or tail, him that bendeth down, or that holdeth back."
        },
        {
          "verse": 16,
          "text": "In that day Egypt shall be like unto women, and they shall be amazed, and afraid, because of the moving of the hand of the Lord of hosts, which he shall move over it."
        },
        {
          "verse": 17,
          "text": "And the land of Juda shall be a terror to Egypt: every one that shall remember it shall tremble, because of the counsel of the Lord of hosts, which he hath determined concerning it."
        },
        {
          "verse": 18,
          "text": "*In that day there shall be five cities in the land of Egypt, speaking the language of Chanaan, and swearing by the Lord of hosts: one shall be called the city of the sun."
        },
        {
          "verse": 19,
          "text": "In that day there shall be an altar of the Lord in the midst of the land of Egypt, and a monument of the Lord at the borders thereof:"
        },
        {
          "verse": 20,
          "text": "It shall be for a sign, and for a testimony to the Lord of hosts in the land of Egypt. For they shall cry to the Lord, because of the oppressor, and he shall send them a Saviour and a defender to deliver them."
        },
        {
          "verse": 21,
          "text": "And the Lord shall be known by Egypt, and the Egyptians shall know the Lord in that day, and shall worship him with sacrifices and offerings: and they shall make vows to the Lord, and perform them."
        },
        {
          "verse": 22,
          "text": "And the Lord shall strike Egypt with a scourge, and shall heal it, and they shall return to the Lord, and he shall be pacified towards them, and heal them."
        },
        {
          "verse": 23,
          "text": "In that day there shall be a way from Egypt to the Assyrians; and the Assyrian shall enter into Egypt; and the Egyptian to the Assyrians; and the Egyptians shall serve the Assyrian."
        },
        {
          "verse": 24,
          "text": "In that day shall Israel be the third to the Egyptian and the Assyrian: a blessing in the midst of the land,"
        },
        {
          "verse": 25,
          "text": "Which the Lord of hosts hath blessed, saying: Blessed be my people of Egypt, and the work of my hands to the Assyrian: but Israel is my inheritance."
        }
      ],
      "verse_count": 25,
      "word_count": 714
    },
    {
      "book": "Matthew",
      "chapter_number": 19,
      "chapter_title": "Matthew 19",
      "verses": [
        {
          "verse": 1,
          "text": "And it came to pass when Jesus had ended these words, he departed from Galilee, *and came into the confines of Judea beyond the Jordan."
        },
        {
          "verse": 2,
          "text": "And great multitudes followed him; and he healed them there."
        },
        {
          "verse": 3,
          "text": "*And the Pharisees came to him tempting him, and saying: Is it lawful for a man to put away his wife for every cause?"
        },
        {
          "verse": 4,
          "text": "But he answering, said to them: Have ye not read, that he *who made man in the beginning, made them male and female? And he said:"
        },
        {
          "verse": 5,
          "text": "*For this cause shall a man leave father and mother, and shall cleave to his wife, and they two shall be in one flesh."
        },
        {
          "verse": 6,
          "text": "Therefore they are no longer two, but one flesh. What therefore God hath joined together, let not man put asunder."
        },
        {
          "verse": 7,
          "text": "They say to him: *Why then did Moses command to give a bill of divorce, and to put away?"
        },
        {
          "verse": 8,
          "text": "He saith to them: Moses because of the hardness of your hearts permitted you to put away your wives: but from the beginning it was not so."
        },
        {
          "verse": 9,
          "text": "*And I say to you, that whosoever shall put away his wife, except it be for fornication, and shall marry another, committeth adultery;: and he who shall marry her that is put away, committeth adultery."
        },
        {
          "verse": 10,
          "text": "His disciples say unto him: If the case of a man with his wife be so, it is not good to marry."
        },
        {
          "verse": 11,
          "text": "He said to them: All receive not this word, but they to whom it is given."
        },
        {
          "verse": 12,
          "text": "For there are eunuchs, who were born so from their mother's womb: and there are eunuchs, who were made so by men: and there are eunuchs, who have made themselves eunuchs for the kingdom of heaven. He that can receive, let him receive it."
        },
        {
          "verse": 13,
          "text": "*Then were little children presented to him, that he should lay his hands upon them and pray. And the disciples rebuked them."
        },
        {
          "verse": 14,
          "text": "But Jesus said to them: *Suffer the little children, and forbid them not to come to me: for the kingdom of heaven is for such."
        },
        {
          "verse": 15,
          "text": "And when he had laid his hands upon them, he departed thence."
        },
        {
          "verse": 16,
          "text": "And behold one came and said to him: Good Master, what good shall I do that I may have life everlasting?"
        },
        {
          "verse": 17,
          "text": "But he said to him: Why asketh thou me concerning good? One is good, God. But if thou wilt enter into life, keep the commandments."
        },
        {
          "verse": 18,
          "text": "He saith to him: Which? And Jesus said: *Thou shalt do no murder, Thou shalt not commit adultery, Thou shalt not steal, Thou shalt not bear false witness."
        },
        {
          "verse": 19,
          "text": "Honour thy father and thy mother: and, Thou shalt love thy neighbour as thyself."
        },
        {
          "verse": 20,
          "text": "The young man saith to him: All these have I kept from my youth: what is yet wanting to me?"
        },
        {
          "verse": 21,
          "text": "Jesus saith to him: If thou wilt be perfect, go sell what thou hast and give to the poor, and thou shalt have treasure in heaven: and come, follow me."
        },
        {
          "verse": 22,
          "text": "And when the young man had heard this word, he went away sad: for he had great possessions."
        },
        {
          "verse": 23,
          "text": "Then Jesus said to his disciples: Amen, I say to you, that a rich man shall hardly enter into the kingdom of heaven."
        },
        {
          "verse": 24,
          "text": "And again I say to you: It is easier for a camel to pass through the eye of a needle, than for a rich man to enter into the kingdom of heaven."
        },
        {
          "verse": 25,
          "text": "And when the disciples had heard this, they wondered very much, saying: Who then can be saved?"
        },
        {
          "verse": 26,
          "text": "And Jesus beholding, said to them: With men this is impossible: but with God all things are possible."
        },
        {
          "verse": 27,
          "text": "Then Peter answering, said to him: Behold we have left all things, and have followed thee: what therefore shall we have?"
        },
        {
          "verse": 28,
          "text": "And Jesus said to them: Amen, I say to you, that you, who have followed me, in the regeneration, when the Son of man shall sit on the seat of his majesty, you also shall sit on twelve seats judging the twelve tribes of Israel."
        },
        {
          "verse": 29,
          "text": "And every one that hath left house, or brethren, or sisters, or father, or mother, or wife, or children, or lands, for my name's sake, shall receive a hundred-fold, and shall possess life everlasting."
        },
        {
          "verse": 30,
          "text": "*But many that are first, shall be last: and the last shall be first."
        }
      ],
      "verse_count": 30,
      "word_count": 711
    }
  ]
}